{"classes":["MEDICINE","DISEASE"],"annotations":[["Paracetamol\r",{"entities":[[0,11,"MEDICINE"]]}],["Aspirin\r",{"entities":[[0,7,"MEDICINE"]]}],["Amoxicillin\r",{"entities":[[0,11,"MEDICINE"]]}],["Omeprazole\r",{"entities":[[0,10,"MEDICINE"]]}],["Metformin\r",{"entities":[[0,9,"MEDICINE"]]}],["Atorvastatin\r",{"entities":[[0,12,"MEDICINE"]]}],["Ibuprofen\r",{"entities":[[0,9,"MEDICINE"]]}],["Azithromycin\r",{"entities":[[0,12,"MEDICINE"]]}],["Ciprofloxacin\r",{"entities":[[0,13,"MEDICINE"]]}],["Ranitidine\r",{"entities":[[0,10,"MEDICINE"]]}],["Diclofenac\r",{"entities":[[0,10,"MEDICINE"]]}],["Pantoprazole\r",{"entities":[[0,12,"MEDICINE"]]}],["Levofloxacin\r",{"entities":[[0,12,"MEDICINE"]]}],["Amlodipine\r",{"entities":[[0,10,"MEDICINE"]]}],["Gabapentin\r",{"entities":[[0,10,"MEDICINE"]]}],["Metronidazole\r",{"entities":[[0,13,"MEDICINE"]]}],["Doxycycline\r",{"entities":[[0,11,"MEDICINE"]]}],["Domperidone\r",{"entities":[[0,11,"MEDICINE"]]}],["Erythromycin\r",{"entities":[[0,12,"MEDICINE"]]}],["Fluconazole\r",{"entities":[[0,11,"MEDICINE"]]}],["Sertraline\r",{"entities":[[0,10,"MEDICINE"]]}],["Losartan\r",{"entities":[]}],["Rosuvastatin\r",{"entities":[]}],["Tramadol\r",{"entities":[[0,8,"MEDICINE"]]}],["Cefixime\r",{"entities":[[0,8,"MEDICINE"]]}],["Ceftriaxone\r",{"entities":[[0,11,"MEDICINE"]]}],["Glimepiride\r",{"entities":[[0,11,"MEDICINE"]]}],["Moxifloxacin\r",{"entities":[[0,12,"MEDICINE"]]}],["Rabeprazole\r",{"entities":[[0,11,"MEDICINE"]]}],["Montelukast\r",{"entities":[[0,11,"MEDICINE"]]}],["Sildenafil\r",{"entities":[[0,10,"MEDICINE"]]}],["Duloxetine\r",{"entities":[[0,10,"MEDICINE"]]}],["Clindamycin\r",{"entities":[[0,11,"MEDICINE"]]}],["Naproxen\r",{"entities":[[0,8,"MEDICINE"]]}],["Pioglitazone\r",{"entities":[[0,12,"MEDICINE"]]}],["Escitalopram\r",{"entities":[[0,12,"MEDICINE"]]}],["Telmisartan\r",{"entities":[[0,11,"MEDICINE"]]}],["Cetirizine\r",{"entities":[[0,10,"MEDICINE"]]}],["Fluticasone\r",{"entities":[[0,11,"MEDICINE"]]}],["Valsartan\r",{"entities":[[0,9,"MEDICINE"]]}],["Dicloxacillin\r",{"entities":[[0,13,"MEDICINE"]]}],["Metoprolol\r",{"entities":[[0,10,"MEDICINE"]]}],["Lorazepam\r",{"entities":[[0,9,"MEDICINE"]]}],["Venlafaxine\r",{"entities":[[0,11,"MEDICINE"]]}],["Levocetirizine\r",{"entities":[[0,14,"MEDICINE"]]}],["Pregabalin\r",{"entities":[[0,10,"MEDICINE"]]}],["Carbamazepine\r",{"entities":[[0,13,"MEDICINE"]]}],["Atorvastatin + Amlodipine\r",{"entities":[[0,12,"MEDICINE"],[15,25,"MEDICINE"]]}],["Aceclofenac\r",{"entities":[[0,11,"MEDICINE"]]}],["Metformin + Glimepiride\r",{"entities":[[0,9,"MEDICINE"],[12,23,"MEDICINE"]]}],["Malaria\r",{"entities":[[0,7,"DISEASE"]]}],["Tuberculosis\r",{"entities":[[0,12,"DISEASE"]]}],["Diabetes\r",{"entities":[[0,8,"DISEASE"]]}],["Hypertension\r",{"entities":[[0,12,"DISEASE"]]}],["Dengue fever\r",{"entities":[[0,6,"DISEASE"],[7,12,"DISEASE"]]}],["Chikungunya\r",{"entities":[[0,11,"DISEASE"]]}],["Typhoid fever\r",{"entities":[[0,7,"DISEASE"],[8,13,"DISEASE"]]}],["Cholera\r",{"entities":[[0,7,"DISEASE"]]}],["Hepatitis\r",{"entities":[[0,9,"DISEASE"]]}],["Cancer\r",{"entities":[[0,6,"DISEASE"]]}],["Influenza\r",{"entities":[[0,9,"DISEASE"]]}],["Pneumonia\r",{"entities":[[0,9,"DISEASE"]]}],["Asthma\r",{"entities":[[0,6,"DISEASE"]]}],["Arthritis\r",{"entities":[[0,9,"DISEASE"]]}],["Osteoporosis\r",{"entities":[[0,12,"DISEASE"]]}],["Alzheimer's disease\r",{"entities":[[0,9,"DISEASE"]]}],["Parkinson's disease\r",{"entities":[[0,9,"DISEASE"]]}],["Stroke\r",{"entities":[[0,6,"DISEASE"]]}],["Heart disease\r",{"entities":[[0,5,"DISEASE"]]}],["Chronic obstructive pulmonary disease (COPD)\r",{"entities":[[0,7,"DISEASE"],[39,43,"DISEASE"]]}],["HIV/AIDS\r",{"entities":[[0,8,"DISEASE"]]}],["Meningitis\r",{"entities":[[0,10,"DISEASE"]]}],["Measles\r",{"entities":[[0,7,"DISEASE"]]}],["Chickenpox\r",{"entities":[[0,10,"DISEASE"]]}],["Rabies\r",{"entities":[[0,6,"DISEASE"]]}],["Leukemia\r",{"entities":[[0,8,"DISEASE"]]}],["Multiple sclerosis\r",{"entities":[[0,8,"DISEASE"],[9,18,"DISEASE"]]}],["Psoriasis\r",{"entities":[[0,9,"DISEASE"]]}],["Gastroenteritis\r",{"entities":[[0,15,"DISEASE"]]}],["Ulcerative colitis\r",{"entities":[[0,18,"DISEASE"]]}],["Crohn's disease\r",{"entities":[[0,15,"DISEASE"]]}],["Glaucoma\r",{"entities":[[0,8,"DISEASE"]]}],["Cataracts\r",{"entities":[[0,9,"DISEASE"]]}],["Epilepsy\r",{"entities":[[0,8,"DISEASE"]]}],["Depression\r",{"entities":[[0,10,"DISEASE"]]}],["Anxiety disorder\r",{"entities":[[0,16,"DISEASE"]]}],["Schizophrenia\r",{"entities":[[0,13,"DISEASE"]]}],["Bipolar disorder\r",{"entities":[[0,16,"DISEASE"]]}],["Autism spectrum disorder\r",{"entities":[[0,24,"DISEASE"]]}],["Down syndrome\r",{"entities":[[0,13,"DISEASE"]]}],["Cerebral palsy\r",{"entities":[[0,14,"DISEASE"]]}],["Ovarian cancer\r",{"entities":[[0,14,"DISEASE"]]}],["Prostate cancer\r",{"entities":[[0,15,"DISEASE"]]}],["Breast cancer\r",{"entities":[[0,13,"DISEASE"]]}],["Lung cancer\r",{"entities":[[0,11,"DISEASE"]]}],["Colon cancer\r",{"entities":[[0,12,"DISEASE"]]}],["Pancreatic cancer\r",{"entities":[[0,17,"DISEASE"]]}],["Leukemia\r",{"entities":[[0,8,"DISEASE"]]}],["Lymphoma\r",{"entities":[[0,8,"DISEASE"]]}],["Kidney disease",{"entities":[[0,14,"DISEASE"]]}]]}